BitVector-3.4.6.html
MANIFEST.in
Makefile
README
setup.py
BitVector/BitVector.py
BitVector/__init__.py
BitVector.egg-info/PKG-INFO
BitVector.egg-info/SOURCES.txt
BitVector.egg-info/dependency_links.txt
BitVector.egg-info/top_level.txt
Examples/BitVectorDemo.py
Examples/README
Examples/testinput1.txt
Examples/testinput4.txt
Examples/testinput5.txt
TestBitVector/BitVector.py
TestBitVector/Test.py
TestBitVector/TestBooleanLogic.py
TestBitVector/TestCircularShifts.py
TestBitVector/TestComparisonOps.py
TestBitVector/TestConstructors.py
TestBitVector/TestPermutations.py
TestBitVector/testinput1.txt
TestBitVector/testinput2.txt
TestBitVector/testinput3.txt
TestBitVector/testinput4.txt
TestBitVector/testinput5.txt
TestBitVector/testinput6.txt
TestBitVector/testinput7.txt