Metadata-Version: 1.1
Name: BitVector
Version: 3.4.6
Summary: A memory-efficient packed representation for bit arrays in pure Python
Home-page: https://engineering.purdue.edu/kak/dist/BitVector-3.4.6.html
Author: Avinash Kak
Author-email: kak@purdue.edu
License: Python Software Foundation License
Download-URL: https://engineering.purdue.edu/kak/dist/BitVector-3.4.6.tar.gz#md5=921cbfad82d0282a3b5aa52eb0f59887
Keywords: bit array,bit vector,bit string,logical operations on bit fields
Platform: All platforms
Classifier: Topic :: Utilities
Classifier: Programming Language :: Python :: 2.7
Classifier: Programming Language :: Python :: 3.5
